CHANGES.rst
COPYRIGHT
LICENSE
MANIFEST.in
README.rst
setup.py
pyramid_asyncio/__init__.py
pyramid_asyncio/aioinspect.py
pyramid_asyncio/authorization.py
pyramid_asyncio/cache.py
pyramid_asyncio/config.py
pyramid_asyncio/kvs.py
pyramid_asyncio/request.py
pyramid_asyncio/router.py
pyramid_asyncio/session.py
pyramid_asyncio/testing.py
pyramid_asyncio/tweens.py
pyramid_asyncio/view.py
pyramid_asyncio/worker.py
pyramid_asyncio.egg-info/PKG-INFO
pyramid_asyncio.egg-info/SOURCES.txt
pyramid_asyncio.egg-info/dependency_links.txt
pyramid_asyncio.egg-info/entry_points.txt
pyramid_asyncio.egg-info/not-zip-safe
pyramid_asyncio.egg-info/requires.txt
pyramid_asyncio.egg-info/top_level.txt
pyramid_asyncio/scaffolds/__init__.py
pyramid_asyncio/scaffolds/__pycache__/__init__.cpython-34.pyc
pyramid_asyncio/scaffolds/aio_jinja2/CHANGES.rst_tmpl
pyramid_asyncio/scaffolds/aio_jinja2/MANIFEST.in_tmpl
pyramid_asyncio/scaffolds/aio_jinja2/README.rst_tmpl
pyramid_asyncio/scaffolds/aio_jinja2/development.ini_tmpl
pyramid_asyncio/scaffolds/aio_jinja2/setup.py_tmpl
pyramid_asyncio/scaffolds/aio_jinja2/+package+/__init__.py_tmpl
pyramid_asyncio/scaffolds/aio_jinja2/+package+/tests.py_tmpl
pyramid_asyncio/scaffolds/aio_jinja2/+package+/views.py_tmpl
pyramid_asyncio/scaffolds/aio_jinja2/+package+/assets/media/pyramid-16x16.png
pyramid_asyncio/scaffolds/aio_jinja2/+package+/templates/hello.jinja2
pyramid_asyncio/scaffolds/aio_jinja2/+package+/templates/layout.jinja2