Metadata-Version: 1.1
Name: pyramid-asyncio
Version: 0.1
Summary: Pyramid Asyncio Glue
Home-page: https://github.com/mardiros/pyramid_asyncio
Author: Guillaume Gauvrit
Author-email: guillaume@gauvr.it
License: BSD-derived (http://www.repoze.org/LICENSE.txt)
Keywords: pyramid asyncio
Platform: UNKNOWN
Classifier: Programming Language :: Python
Classifier: Programming Language :: Python :: 3.3
Classifier: Programming Language :: Python :: 3.4
Classifier: Framework :: Pyramid
Classifier: Topic :: Internet :: WWW/HTTP
Classifier: Topic :: Internet :: WWW/HTTP :: WSGI :: Application
Classifier: Intended Audience :: Developers
Classifier: License :: Repoze Public License
